MANIFEST.in
distribute_setup.py
setup.py
src/jsonpipe/__init__.py
src/jsonpipe/pipe.py
src/jsonpipe/sh.py
src/jsonpipe.egg-info/PKG-INFO
src/jsonpipe.egg-info/SOURCES.txt
src/jsonpipe.egg-info/dependency_links.txt
src/jsonpipe.egg-info/entry_points.txt
src/jsonpipe.egg-info/requires.txt
src/jsonpipe.egg-info/top_level.txt