Metadata-Version: 1.0
Name: jsonpipe
Version: 0.0.8
Summary: Convert JSON to a UNIX-friendly line-based format.
Home-page: http://github.com/dvxhouse/jsonpipe
Author: Zachary Voase
Author-email: z@dvxhouse.com
License: UNKNOWN
Platform: UNKNOWN
